MANIFEST.in
Makefile
README.rst
setup.py
docker_emperor/__init__.py
docker_emperor/__init__.pyc
docker_emperor/exceptions.py
docker_emperor/exceptions.pyc
docker_emperor/logger.py
docker_emperor/logger.pyc
docker_emperor/main.pyc
docker_emperor/root.py
docker_emperor/root.pyc
docker_emperor/utils.py
docker_emperor/utils.pyc
docker_emperor.egg-info/PKG-INFO
docker_emperor.egg-info/SOURCES.txt
docker_emperor.egg-info/dependency_links.txt
docker_emperor.egg-info/entry_points.txt
docker_emperor.egg-info/requires.txt
docker_emperor.egg-info/top_level.txt
docker_emperor/bin/managehosts
docker_emperor/commands/__init__.py
docker_emperor/commands/__init__.pyc
docker_emperor/commands/aliases.py
docker_emperor/commands/bash.py
docker_emperor/commands/bash.pyc
docker_emperor/commands/build.py
docker_emperor/commands/build.pyc
docker_emperor/commands/create.py
docker_emperor/commands/create.pyc
docker_emperor/commands/down.py
docker_emperor/commands/down.pyc
docker_emperor/commands/exec.py
docker_emperor/commands/exec.pyc
docker_emperor/commands/info.py
docker_emperor/commands/info.pyc
docker_emperor/commands/launch.py
docker_emperor/commands/launch.pyc
docker_emperor/commands/logs.py
docker_emperor/commands/logs.pyc
docker_emperor/commands/mount.py
docker_emperor/commands/mount.pyc
docker_emperor/commands/prune.py
docker_emperor/commands/prune.pyc
docker_emperor/commands/ps.py
docker_emperor/commands/ps.pyc
docker_emperor/commands/rebuild.py
docker_emperor/commands/rebuild.pyc
docker_emperor/commands/regenerate-certs.py
docker_emperor/commands/regenerate-certs.pyc
docker_emperor/commands/remove.py
docker_emperor/commands/remove.pyc
docker_emperor/commands/restart.py
docker_emperor/commands/restart.pyc
docker_emperor/commands/run.py
docker_emperor/commands/run.pyc
docker_emperor/commands/ssh.py
docker_emperor/commands/ssh.pyc
docker_emperor/commands/start.py
docker_emperor/commands/start.pyc
docker_emperor/commands/status.py
docker_emperor/commands/status.pyc
docker_emperor/commands/stop.py
docker_emperor/commands/stop.pyc
docker_emperor/commands/switch.py
docker_emperor/commands/syncfiles.py
docker_emperor/commands/syncfiles.pyc
docker_emperor/commands/top.py
docker_emperor/commands/top.pyc
