Metadata-Version: 1.1
Name: docker-emperor
Version: 0.2.2
Summary: Docker CLI that combine compose and machine for a full stack deployment
Home-page: https://pypi.org/project/docker-emperor
Author: Damien Autrusseau
Author-email: damien.autrusseau@gmail.com
License: Apache Software License
Platform: UNKNOWN
Classifier: Development Status :: 3 - Alpha
Classifier: Programming Language :: Python
Classifier: Topic :: Utilities
Classifier: License :: OSI Approved :: Apache Software License
Classifier: Operating System :: OS Independent
